superset_toolkit/__init__.py
superset_toolkit/auth.py
superset_toolkit/charts.py
superset_toolkit/cli.py
superset_toolkit/client.py
superset_toolkit/config.py
superset_toolkit/dashboard.py
superset_toolkit/datasets.py
superset_toolkit/ensure.py
superset_toolkit/exceptions.py
superset_toolkit/queries.py
superset_toolkit/utils/__init__.py
superset_toolkit/utils/metrics.py
superset_toolkit-0.2.2.dist-info/METADATA
superset_toolkit-0.2.2.dist-info/WHEEL
superset_toolkit-0.2.2.dist-info/entry_points.txt
superset_toolkit-0.2.2.dist-info/top_level.txt
superset_toolkit-0.2.2.dist-info/RECORD
