Metadata-Version: 2.4
Name: superset-toolkit
Version: 0.2.2
Summary: Professional toolkit for Superset API automation - datasets, charts, and dashboards
Author: Open Source Contributors
License-Expression: MIT
Project-URL: Homepage, https://github.com/daviddallakyan2005/superset-toolkit
Project-URL: Repository, https://github.com/daviddallakyan2005/superset-toolkit.git
Project-URL: Documentation, https://github.com/daviddallakyan2005/superset-toolkit#readme
Project-URL: Issues, https://github.com/daviddallakyan2005/superset-toolkit/issues
Keywords: superset,dashboard,automation,api,charts,datasets
Classifier: Development Status :: 4 - Beta
Classifier: Intended Audience :: Developers
Classifier: Programming Language :: Python :: 3
Classifier: Programming Language :: Python :: 3.10
Classifier: Programming Language :: Python :: 3.11
Classifier: Programming Language :: Python :: 3.12
Classifier: Topic :: Software Development :: Libraries :: Python Modules
Classifier: Topic :: Database
Classifier: Topic :: Scientific/Engineering :: Visualization
Requires-Python: >=3.10
Requires-Dist: requests>=2.31.0
Requires-Dist: typing-extensions>=4.0.0
Provides-Extra: dev
Requires-Dist: pytest>=7.0.0; extra == "dev"
Requires-Dist: pytest-cov>=4.0.0; extra == "dev"
Requires-Dist: black>=23.0.0; extra == "dev"
Requires-Dist: isort>=5.12.0; extra == "dev"
Requires-Dist: mypy>=1.0.0; extra == "dev"
Requires-Dist: pre-commit>=3.0.0; extra == "dev"
Provides-Extra: cli
Requires-Dist: typer[all]>=0.9.0; extra == "cli"
Requires-Dist: rich>=13.0.0; extra == "cli"
